broken/__init__.py
broken/example.py
broken_python-0.1.0.dist-info/licenses/LICENSE
broken_python-0.1.0.dist-info/METADATA
broken_python-0.1.0.dist-info/WHEEL
broken_python-0.1.0.dist-info/top_level.txt
broken_python-0.1.0.dist-info/RECORD
